AUTHORS
LICENSE
MANIFEST.in
README.md
bingsearch.py
setup.py
bingsearch.egg-info/PKG-INFO
bingsearch.egg-info/SOURCES.txt
bingsearch.egg-info/dependency_links.txt
bingsearch.egg-info/requires.txt
bingsearch.egg-info/top_level.txt