Metadata-Version: 1.0
Name: bingsearch
Version: 0.1
Summary: A simple python wrapper for the Azure Bing Search API.
Home-page: http://github.com/guitarparty/bingsearch
Author: Guitarparty.com
Author-email: oss@guitarparty.com
License: MIT
Platform: any
Classifier: Development Status :: 4 - Beta
Classifier: Intended Audience :: Developers
Classifier: License :: OSI Approved :: MIT License
Classifier: Operating System :: OS Independent
Classifier: Programming Language :: Python
Classifier: Topic :: Software Development :: Libraries :: Python Modules
